quantit_snapshot/__init__.py
quantit_snapshot/base/__init__.py
quantit_snapshot/base/args/__init__.py
quantit_snapshot/base/args/smargs.py
quantit_snapshot/base/meta/__init__.py
quantit_snapshot/base/meta/meta.py
quantit_snapshot/base/setting/__init__.py
quantit_snapshot/base/setting/settings.py
quantit_snapshot/base/setting/venv/__init__.py
quantit_snapshot/base/setting/venv/helper.py
quantit_snapshot/data/__init__.py
quantit_snapshot/data/snapshot.py
quantit_snapshot/production/__init__.py
quantit_snapshot/production/submit.py
quantit_snapshot/util/__init__.py
quantit_snapshot/util/cloud/__init__.py
quantit_snapshot/util/cloud/aws/__init__.py
quantit_snapshot/util/cloud/aws/s3_quanda_ex.py
quantit_snapshot/util/config/__init__.py
quantit_snapshot/util/config/db/__init__.py
quantit_snapshot/util/config/db/db.py
quantit_snapshot/util/config/log/__init__.py
quantit_snapshot/util/config/log/file.py
quantit_snapshot/util/config/log/log.py
quantit_snapshot/util/config/log/slack.py
quantit_snapshot/util/db/__init__.py
quantit_snapshot/util/db/alchemy.py
quantit_snapshot/util/db/db.py
quantit_snapshot/util/db/orm/__init__.py
quantit_snapshot/util/db/orm/snapshot.py
test/__init__.py
test/test_base_sm.py
quantit_snapshot-0.0.1.dist-info/METADATA
quantit_snapshot-0.0.1.dist-info/WHEEL
quantit_snapshot-0.0.1.dist-info/top_level.txt
quantit_snapshot-0.0.1.dist-info/RECORD
