Metadata-Version: 2.1
Name: quantit-snapshot
Version: 0.0.1
Summary: quantit snapshot util package
Home-page: http://gitlab.quantit.io/quanda/snapshot_utils.git
Author: hoseung2
Author-email: hoseung2@quantit.io
License: UNKNOWN
Platform: UNKNOWN
Classifier: Programming Language :: Python :: 3
Classifier: License :: OSI Approved :: MIT License
Classifier: Operating System :: OS Independent
Requires-Python: >=3.6
Requires-Dist: pydantic (<2.0.0)
Requires-Dist: boto3 (>=1.14.54)
Requires-Dist: numpy (>=1.14.0)
Requires-Dist: pandas (>=0.22.0)
